d4k_ms_base/__info__.py
d4k_ms_base/__init__.py
d4k_ms_base/errors_and_logging.py
d4k_ms_base/logger.py
d4k_ms_base/service.py
d4k_ms_base/service_environment.py
d4k_ms_base-0.4.0.dist-info/licenses/LICENSE
d4k_ms_base-0.4.0.dist-info/METADATA
d4k_ms_base-0.4.0.dist-info/WHEEL
d4k_ms_base-0.4.0.dist-info/top_level.txt
d4k_ms_base-0.4.0.dist-info/RECORD
